multisafepay/__init__.py
multisafepay/api/__init__.py
multisafepay/api/base/__init__.py
multisafepay/api/base/abstract_manager.py
multisafepay/api/base/decorator.py
multisafepay/api/base/listings/__init__.py
multisafepay/api/base/listings/cursor.py
multisafepay/api/base/listings/listing.py
multisafepay/api/base/listings/listing_pager.py
multisafepay/api/base/listings/pager.py
multisafepay/api/base/response/__init__.py
multisafepay/api/base/response/api_response.py
multisafepay/api/base/response/custom_api_response.py
multisafepay/api/paths/__init__.py
multisafepay/api/paths/auth/__init__.py
multisafepay/api/paths/auth/api_token/__init__.py
multisafepay/api/paths/auth/api_token/response/__init__.py
multisafepay/api/paths/auth/api_token/response/api_token.py
multisafepay/api/paths/auth/auth_manager.py
multisafepay/api/paths/capture/__init__.py
multisafepay/api/paths/capture/capture_manager.py
multisafepay/api/paths/capture/request/__init__.py
multisafepay/api/paths/capture/request/capture_request.py
multisafepay/api/paths/capture/response/__init__.py
multisafepay/api/paths/capture/response/capture.py
multisafepay/api/paths/categories/__init__.py
multisafepay/api/paths/categories/category_manager.py
multisafepay/api/paths/categories/response/__init__.py
multisafepay/api/paths/categories/response/category.py
multisafepay/api/paths/gateways/__init__.py
multisafepay/api/paths/gateways/gateway_manager.py
multisafepay/api/paths/gateways/response/__init__.py
multisafepay/api/paths/gateways/response/gateway.py
multisafepay/api/paths/issuers/__init__.py
multisafepay/api/paths/issuers/issuer_manager.py
multisafepay/api/paths/issuers/response/__init__.py
multisafepay/api/paths/issuers/response/issuer.py
multisafepay/api/paths/me/__init__.py
multisafepay/api/paths/me/me_manager.py
multisafepay/api/paths/me/response/__init__.py
multisafepay/api/paths/me/response/me.py
multisafepay/api/paths/orders/__init__.py
multisafepay/api/paths/orders/order_id/__init__.py
multisafepay-2.1.0.dist-info/LICENSE.md
multisafepay-2.1.0.dist-info/METADATA
multisafepay-2.1.0.dist-info/WHEEL
multisafepay-2.1.0.dist-info/RECORD
