Metadata-Version: 2.3
Name: multisafepay
Version: 2.1.0
Summary: Multisafepay API wrapper
License: OSL-3.0
Author: Multisafepay
Author-email: integration@multisafepay.com
Requires-Python: >=3.9,<3.14
Classifier: License :: OSI Approved
Classifier: Programming Language :: Python :: 3
Classifier: Programming Language :: Python :: 3.9
Classifier: Programming Language :: Python :: 3.10
Classifier: Programming Language :: Python :: 3.11
Classifier: Programming Language :: Python :: 3.12
Classifier: Programming Language :: Python :: 3.13
Requires-Dist: pydantic (>=1.10.0,<2.0.0)
Requires-Dist: python-dotenv (>=1.0.1,<2.0.0)
Requires-Dist: requests (>=2.32.4,<3.0.0)
Requires-Dist: urllib3 (>=2.5.0)
Project-URL: Homepage, https://multisafepay.com
Project-URL: Repository, https://github.com/MultiSafepay/python-sdk
